MANIFEST.in
README.txt
buildout.cfg
setup.cfg
setup.py
docs/HISTORY.txt
docs/INSTALL.txt
docs/LICENSE.GPL
docs/LICENSE.txt
unimr/__init__.py
unimr.red5.protectedvod.egg-info/PKG-INFO
unimr.red5.protectedvod.egg-info/SOURCES.txt
unimr.red5.protectedvod.egg-info/dependency_links.txt
unimr.red5.protectedvod.egg-info/entry_points.txt
unimr.red5.protectedvod.egg-info/namespace_packages.txt
unimr.red5.protectedvod.egg-info/not-zip-safe
unimr.red5.protectedvod.egg-info/requires.txt
unimr.red5.protectedvod.egg-info/top_level.txt
unimr/red5/__init__.py
unimr/red5/protectedvod/__init__.py
unimr/red5/protectedvod/config.py
unimr/red5/protectedvod/configure.zcml
unimr/red5/protectedvod/interfaces.py
unimr/red5/protectedvod/overrides.zcml
unimr/red5/protectedvod/permissions.py
unimr/red5/protectedvod/setuphandlers.py
unimr/red5/protectedvod/tests.py
unimr/red5/protectedvod/utils.py
unimr/red5/protectedvod/version.txt
unimr/red5/protectedvod/content/__init__.py
unimr/red5/protectedvod/content/red5stream.py
unimr/red5/protectedvod/interface/__init__.py
unimr/red5/protectedvod/interface/red5stream.py
unimr/red5/protectedvod/profiles/default/import_steps.xml
unimr/red5/protectedvod/profiles/default/jsregistry.xml
unimr/red5/protectedvod/profiles/default/metadata.xml
unimr/red5/protectedvod/profiles/default/propertiestool.xml
unimr/red5/protectedvod/profiles/default/skins.xml
unimr/red5/protectedvod/profiles/default/types.xml
unimr/red5/protectedvod/profiles/default/types/Red5Stream.xml
unimr/red5/protectedvod/red5-webapp/README.txt
unimr/red5/protectedvod/red5-webapp/protectedVOD_0.1-java6.war
unimr/red5/protectedvod/red5-webapp/protectedVOD_0.1-src.tgz
unimr/red5/protectedvod/skins/unimr_red5_protectedvod/flowplayer-3.1.2.min.js
unimr/red5/protectedvod/skins/unimr_red5_protectedvod/flowplayer-3.1.2.swf
unimr/red5/protectedvod/skins/unimr_red5_protectedvod/flowplayer-3.1.2.swf.metadata
unimr/red5/protectedvod/skins/unimr_red5_protectedvod/flowplayer-protectedvod.js
unimr/red5/protectedvod/skins/unimr_red5_protectedvod/flowplayer.cluster-3.1.0.swf
unimr/red5/protectedvod/skins/unimr_red5_protectedvod/flowplayer.controls-3.1.2.swf
unimr/red5/protectedvod/skins/unimr_red5_protectedvod/flowplayer.controls-3.1.2.swf.metadata
unimr/red5/protectedvod/skins/unimr_red5_protectedvod/flowplayer.rtmp-3.1.1.swf
