Metadata-Version: 1.0
Name: unimr.red5.protectedvod
Version: 0.1rc1-r96721
Summary: Manage, protect and present your video/audio content (FLV, MP3, etc.) with Plone but delegate the flash streaming to Red5
Home-page: http://svn.plone.org/svn/collective/unimr.red5.protectedvod
Author: Andreas Gabriel
Author-email: gabriel@hrz.uni-marburg.de
License: GPL
Keywords: Plone Flash FLV MP3 Zope Streaming Red5 rtmp
Platform: UNKNOWN
Classifier: Framework :: Plone
Classifier: Programming Language :: Python
Classifier: Topic :: Software Development :: Libraries :: Python Modules
Classifier: Topic :: Multimedia :: Video
Classifier: Topic :: Multimedia :: Sound/Audio
